{"url":"http://www.environmentalgraffiti.com/businesspolitics/what’s-that-dear-around-500-us-cosmetics-are-unsafe/309","content":"\nYou bet your ass they are. Well…that’s according to US NGO, the Environmental Working Group. The group has published research, revealing that 478 cosmetic products sold in the US contain doses of toxic chemicals which are unsafe, even when used as directed on the bottle! These would simply not be allowed in Canada, Japan or the EU.\n23,000 beauty products were tested and 751 failed to meet one or more US government safety standard. Large quantities of formaldehyde, selenium, hydrogen peroxide and lead acetate were found.\nEnvironmental Graffiti has discovered this week, that the Environmental Working Group has been banned from a US Food and Drugs administration meeting, discussing the international trade of cosmetics. Coincidence? The FDA, unsurprisingly say so – they want an 'industry association-regulator dialogue.' \nRichard Wiles Executive Director of NGO however, is not a happy bunny. According to the Ecologist magazine:","web_category":"lifestyle","advice_category":"8","picture_url":"http://static.environmentalgraffiti.com/sites/default/files/imagecache/promoted/images/http-inlinethumb24.webshots.com-44055-2359028470104181437S600x600Q85.jpg","title":"What’s that dear? Around 500 US cosmetics are unsafe?","author":"Chris"}