{"url":"http://www.environmentalgraffiti.com/featured/buildings-have-faces-too/12382","content":"\n\nImage: \nDon’t you love it when you find beauty in places you least expect it? Like seeing a smiley face on a grey, dreary day? Around the world, people find buildings with faces in their neighbourhood and attribute human characteristics to them. The following pictures prove that some buildings truly have character. \n\nImage: \n\nImage: \n\nImage: \n\nImage: \n\nImage: \n\nImage: \n\nImage: \n\nImage: \n\nImage via \n\nImage: \n\nImage: \n\nImage: \n\nImage: \n\nImage: \n\nImage: \n\nImage: \n\n","web_category":"art+and+design","advice_category":"6","picture_url":"http://static.environmentalgraffiti.com/sites/default/files/imagecache/promoted/images/lw15.jpg","title":"Buildings Have Faces Too!","author":"Simone Preuss"}