{"summary":"Slope textures of a crater in Terra Cimmeria. A \"peninsula\" surrounded by a \"sea\" of dunes in the Ganges Chasma","advice_category":"4","content":"While NASA's Mars rover inches closer to finding evidence of ancient life on Mars, a $40 million high resolution camera called HiRISE is capturing beautiful, abstract satellite photos from 15,000 miles above the ochre surface.\n\nPhoto: NASA/JPL/University of Arizona\n\nSlope textures of a crater in Terra Cimmeria\n?\n\n* * *?\n?\n\nPhoto: NASA/JPL/University of Arizona\n\nSand dunes in Her Desher Vallis\n?\n\n* * *?\n?\n\nPhoto: NASA/JPL/University of Arizona\n\nPit in Daedalia Planum, south of Arsia Mons\n?\n\n* * *?\n?\n\nPhoto: NASA/JPL/University of Arizona\n\nTraveling boulder in Nili Fossae\n?\n\n* * *?\n?\n\nPhoto: NASA/JPL/University of Arizona\n\nA \"peninsula\" surrounded by a \"sea\" of dunes in the Ganges Chasma\n?\n\n* * *?\n?\n\nPhoto: NASA/JPL/University of Arizona\n\nGullies in Kaiser Crater\n?\n\n* * *?\n?\n\nPhoto: NASA/JPL/University of Arizona\n\nCratered cone in Chrysa Planitia\n?\n\n* * *?\n?\n\nPhoto: NASA/JPL/University of Arizona\n\nSlope textures of a crater in Coprates Chasma\n?\n\n* * *?\n?\n\nPhoto: NASA/JPL/University of Arizona\n\nDunes sculpted by the wind\n?\n\n* * *?\n?\n\nPhoto: NASA/JPL/University of Arizona\n\nValleys in Tyrrhena Terra\n?\n\n* * *?\n?\n\nPhoto: NASA/JPL/University of Arizona\n\nThousands of small craters within the Bombala Crater\n?\n\n* * *?\n?\n\nPhoto: NASA/JPL/University of Arizona\n\nHolden Crater \u2014 possible landing site for future missions\n?\n\n* * *?\n?\n\nPhoto: NASA/JPL/University of Arizona\n\nLake deposit in open basin\n?\n\n* * *?\n?\nCatie Leary is a photo editor at Mother Nature Network. Follow her on Twitter and Google+.\n?\nRelated content on MNN:\n\nIt's time to get serious about going to Mars, says NASA\n\n\nMars-bound astronauts will face high risk of cosmic radiation\n\n\nWant to see more great photos??Check out our Big Snapshot archive","author":"","web_category":"earth-matters#space","title":"13 jaw-dropping images of Martian terrain","picture_url":"","url":"http://www.mnn.com//earth-matters/space/blogs/13-jaw-dropping-images-of-martian-terrain"}